{
  "name": "Flying_Campus_Map",
  "type": "GameObject",
  "static": true,
  "outdated": false,
  "uuid": "F551BF3D-5789-4A08-93EF-1DFFDCB04899",
  "parentUUID": null,
  "components": {
    "Render": {
      "uuid": "8AC37575-F2D4-4906-B512-AC09F56DC7F4",
      "name": null,
      "media": null,
      "type": "Render",
      "idModel": "flying_campus",
      "color": [1, 1, 1]
    },
    "WorldScript": {
      "uuid": "3B37FCEC-F920-4B87-A7F5-499FDED44877",
      "idScripts": ["map"],
      "conf": {
        "heightmap_path": "./assets/heightmap/flying_campus.png",
        "heightmap_geometry": {
          "bounding_box": {
            "min": { "x": 0, "y": 0, "z": 0 },
            "max": {
              "x": 213.26456154806635,
              "y": 217.67993360188194,
              "z": 179.05260716867784
            }
          },
          "heightmap_min": 76.93562108253147,
          "heightmap_max": 139.66103359156872
        }
      },
      "type": "WorldScript"
    }
  },
  "children": [
    {
      "name": "Zeppelin",
      "type": "GameObject",
      "static": false,
      "outdated": false,
      "uuid": "18C43BC9-D445-45DD-9CC2-357A5CF6F389",
      "parentUUID": null,
      "components": {
        "Render": {
          "uuid": "8732545C-3E5D-4A74-8273-66E91F756512",
          "name": null,
          "media": null,
          "type": "Render",
          "idModel": "zeppelin",
          "color": [1, 1, 1]
        },
        "WorldScript": {
          "uuid": "8298A71C-E680-4924-9D0A-2716E42E0540",
          "idScripts": ["zeppelin"],
          "conf": {
            "duration": 1000
          },
          "type": "WorldScript"
        }
      },
      "children": [],
      "transform": {
        "position": { "x": 0, "y": 0, "z": 0 },
        "rotation": { "x": 0, "y": 0, "z": 0 },
        "scale": { "x": 1, "y": 1, "z": 1 }
      }
    }
  ],
  "transform": {
    "position": { "x": 0, "y": 0, "z": 0 },
    "rotation": { "x": 0, "y": 0, "z": 0 },
    "scale": { "x": 1, "y": 1, "z": 1 }
  }
}
